<attr><ref type="cell" ref="A2"><font-weight>bold</font-weight></ref><ref type="cell" ref="A9"><value><string>Current Tax Code</string></value></ref><ref type="cell" ref="A5"><value><string>Postcode</string></value></ref><ref type="column" ref="A"><width>114</width></ref><ref type="cell" ref="A1"><value><string>First Name</string></value></ref><ref type="cell" ref="B1"><color>black</color></ref><ref type="cell" ref="A1"><formula>First Name</formula></ref><ref type="cell" ref="A5"><font-weight>bold</font-weight></ref><ref type="cell" ref="A1"><color>black</color></ref><ref type="cell" ref="A2"><value><string>Surname</string></value></ref><ref type="cell" ref="B1"><value><string>Lee</string></value></ref><ref type="cell" ref="B4"><rawvalue><string>Bo'ness</string></rawvalue></ref><ref type="cell" ref="A3"><color>black</color></ref><ref type="cell" ref="B2"><rawvalue><string>Hazelwood</string></rawvalue></ref><ref type="cell" ref="A9"><rawvalue><string>Current Tax Code</string></rawvalue></ref><ref type="cell" ref="A7"><font-weight>bold</font-weight></ref><ref type="cell" ref="B7"><color>black</color></ref><ref type="cell" ref="A3"><rawvalue><string>Address</string></rawvalue></ref><ref type="cell" ref="A3"><formula>Address</formula></ref><ref type="cell" ref="B5"><rawvalue><string>EH45 3BT</string></rawvalue></ref><ref type="cell" ref="B1"><formula>Lee</formula></ref><ref type="cell" ref="A3"><value><string>Address</string></value></ref><ref type="cell" ref="B4"><formula>Bo'ness</formula></ref><ref type="cell" ref="A7"><value><string>NI Number</string></value></ref><ref type="cell" ref="B7"><rawvalue><string>AA 44 25 11 C</string></rawvalue></ref><ref type="cell" ref="A7"><color>black</color></ref><ref type="cell" ref="B2"><formula>Hazelwood</formula></ref><ref type="cell" ref="A9"><color>black</color></ref><ref type="cell" ref="A9"><formula>Current Tax Code</formula></ref><ref type="cell" ref="A1"><rawvalue><string>First Name</string></rawvalue></ref><ref type="cell" ref="A7"><formula>NI Number</formula></ref><ref type="cell" ref="B4"><color>black</color></ref><ref type="cell" ref="B3"><rawvalue><string>12 Dean Court</string></rawvalue></ref><ref type="cell" ref="B3"><color>black</color></ref><ref type="cell" ref="A2"><rawvalue><string>Surname</string></rawvalue></ref><ref type="cell" ref="B5"><color>black</color></ref><ref type="cell" ref="A5"><formula>Postcode</formula></ref><ref type="cell" ref="A3"><font-weight>bold</font-weight></ref><ref type="cell" ref="B3"><value><string>12 Dean Court</string></value></ref><ref type="cell" ref="B2"><value><string>Hazelwood</string></value></ref><ref type="cell" ref="A7"><rawvalue><string>NI Number</string></rawvalue></ref><ref type="cell" ref="A2"><color>black</color></ref><ref type="cell" ref="B7"><formula>AA 44 25 11 C</formula></ref><ref type="cell" ref="B5"><value><string>EH45 3BT</string></value></ref><ref type="cell" ref="A5"><color>black</color></ref><ref type="cell" ref="B1"><rawvalue><string>Lee</string></rawvalue></ref><ref type="cell" ref="B3"><formula>12 Dean Court</formula></ref><ref type="cell" ref="B4"><value><string>Bo'ness</string></value></ref><ref type="cell" ref="A9"><font-weight>bold</font-weight></ref><ref type="cell" ref="A1"><font-weight>bold</font-weight></ref><ref type="cell" ref="B5"><formula>EH45 3BT</formula></ref><ref type="cell" ref="A5"><rawvalue><string>Postcode</string></rawvalue></ref><ref type="cell" ref="B7"><value><string>AA 44 25 11 C</string></value></ref><ref type="cell" ref="B2"><color>black</color></ref><ref type="cell" ref="A2"><formula>Surname</formula></ref></attr>