{"time":1273599616338124,"user":"anonymous","host":"http://e.hypernumbers.dev:9000","lang":"en_gb","groups":[],"permissions":{"champion":"_g/core/webpage","challenger":[],"views":{"_g/core/spreadsheet":{"everyone":false,"groups":["admin"]},"_g/core/webpage":{"everyone":true,"groups":["admin"]}}},"page":{},"styles":{"3":"color:#000000;background-color:#B7CA79;font-weight:bold;font-size:220%;text-align:center;","2":"text-align:left;","1":"text-align:center;"},"row":{"11":{"11":{"height":20,"fixedHeight":true}}},"column":{},"cell":{"23":{"5":{"style":1},"2":{"style":1},"9":{"style":1},"6":{"style":1},"3":{"style":1},"7":{"style":1},"4":{"style":1},"8":{"style":1}},"41":{"2":{"style":1},"3":{"style":1}},"58":{"2":{"style":1},"3":{"style":1}},"76":{"2":{"style":1},"3":{"style":1}},"2":{"2":{"rawvalue":"<div class='hn_inner' style='width:640px'><div style='left:0px;top:0px;width:400px;height:57px;text-align:left;'><img src=\"http://imgur.com/ECUN6.png\"></div><div style='left:400px;top:0px;width:80px;height:20px;text-align:left;'></div><div style='left:480px;top:0px;width:80px;height:20px;text-align:left;'></div><div style='left:0px;top:57px;width:160px;height:61px;font-size:180%;font-family:trebuchet ms, sans-serif;text-align:left;'><a href=\"/\">Home</a></div><div style='left:160px;top:57px;width:160px;height:61px;font-size:180%;font-family:trebuchet ms, sans-serif;text-align:left;'><a href=\"/about/\">About Us</a></div><div style='left:320px;top:57px;width:160px;height:61px;font-size:180%;font-family:trebuchet ms, sans-serif;text-align:left;'><a href=\"/contact/\">Contact</a></div><div style='left:480px;top:57px;width:80px;height:61px;font-size:180%;font-family:trebuchet ms, sans-serif;text-align:left;'><a href=\"/help/\">Help</a></div><div style='left:560px;top:57px;width:80px;height:25px;text-align:left;'><a href=\"http://www.twitter.com/hypernumbers\"><img src=\"http://twitter-badges.s3.amazonaws.com/t_small-b.png\" alt=\"Follow hypernumbers on Twitter\"/></a></div><div style='left:560px;top:82px;width:80px;height:36px;text-align:left;'><a name=\"fb_share\" type=\"box_count\"  href=\"http://www.facebook.com/sharer.php\">Share</a><script src=\"http://static.ak.fbcdn.net/connect.php/js/FB.Share\" type=\"text/javascript\"></script></div><div style='left:0px;top:118px;width:80px;height:1px;color:#FFFFFF;background-color:#89725B;'></div><div style='left:80px;top:118px;width:80px;height:1px;color:#FFFFFF;background-color:#89725B;'></div><div style='left:160px;top:118px;width:80px;height:1px;color:#FFFFFF;background-color:#89725B;'></div><div style='left:240px;top:118px;width:80px;height:1px;color:#FFFFFF;background-color:#89725B;'></div><div style='left:320px;top:118px;width:80px;height:1px;color:#FFFFFF;background-color:#89725B;'></div><div style='left:400px;top:118px;width:80px;height:1px;color:#FFFFFF;background-color:#89725B;'></div><div style='left:480px;top:118px;width:80px;height:1px;color:#FFFFFF;background-color:#89725B;'></div><div style='left:560px;top:118px;width:80px;height:1px;color:#FFFFFF;background-color:#89725B;'></div></div>","formula":"=include(/B2:I7)","merge":{"right":7,"down":5},"parents":"bleh","value":"<div class='hn_inner' style='width:640px'><div style='left:0px;top:0px;width:400px;height:57px;text-align:left;'><img src=\"http://imgur.com/ECUN6.png\"></div><div style='left:400px;top:0px;width:80px;height:20px;text-align:left;'></div><div style='left:480px;top:0px;width:80px;height:20px;text-align:left;'></div><div style='left:0px;top:57px;width:160px;height:61px;font-size:180%;font-family:trebuchet ms, sans-serif;text-align:left;'><a href=\"/\">Home</a></div><div style='left:160px;top:57px;width:160px;height:61px;font-size:180%;font-family:trebuchet ms, sans-serif;text-align:left;'><a href=\"/about/\">About Us</a></div><div style='left:320px;top:57px;width:160px;height:61px;font-size:180%;font-family:trebuchet ms, sans-serif;text-align:left;'><a href=\"/contact/\">Contact</a></div><div style='left:480px;top:57px;width:80px;height:61px;font-size:180%;font-family:trebuchet ms, sans-serif;text-align:left;'><a href=\"/help/\">Help</a></div><div style='left:560px;top:57px;width:80px;height:25px;text-align:left;'><a href=\"http://www.twitter.com/hypernumbers\"><img src=\"http://twitter-badges.s3.amazonaws.com/t_small-b.png\" alt=\"Follow hypernumbers on Twitter\"/></a></div><div style='left:560px;top:82px;width:80px;height:36px;text-align:left;'><a name=\"fb_share\" type=\"box_count\"  href=\"http://www.facebook.com/sharer.php\">Share</a><script src=\"http://static.ak.fbcdn.net/connect.php/js/FB.Share\" type=\"text/javascript\"></script></div><div style='left:0px;top:118px;width:80px;height:1px;color:#FFFFFF;background-color:#89725B;'></div><div style='left:80px;top:118px;width:80px;height:1px;color:#FFFFFF;background-color:#89725B;'></div><div style='left:160px;top:118px;width:80px;height:1px;color:#FFFFFF;background-color:#89725B;'></div><div style='left:240px;top:118px;width:80px;height:1px;color:#FFFFFF;background-color:#89725B;'></div><div style='left:320px;top:118px;width:80px;height:1px;color:#FFFFFF;background-color:#89725B;'></div><div style='left:400px;top:118px;width:80px;height:1px;color:#FFFFFF;background-color:#89725B;'></div><div style='left:480px;top:118px;width:80px;height:1px;color:#FFFFFF;background-color:#89725B;'></div><div style='left:560px;top:118px;width:80px;height:1px;color:#FFFFFF;background-color:#89725B;'></div></div>","style":2,"overwrite-color":"auto"}},"20":{"5":{"style":1},"2":{"style":1},"9":{"style":1},"6":{"style":1},"3":{"style":1},"7":{"style":1},"4":{"style":1},"8":{"style":1}},"19":{"5":{"style":1},"2":{"style":1},"9":{"style":1},"6":{"style":1},"3":{"style":1},"7":{"style":1},"4":{"style":1},"8":{"style":1}},"37":{"2":{"style":1},"3":{"style":1}},"55":{"2":{"style":1},"3":{"style":1}},"73":{"2":{"style":1},"3":{"style":1}},"16":{"5":{"style":1},"2":{"style":1},"9":{"style":1},"6":{"style":1},"3":{"style":1},"7":{"style":1},"4":{"style":1},"8":{"style":1}},"34":{"2":{"style":1},"3":{"style":1}},"52":{"2":{"style":1},"3":{"style":1}},"70":{"2":{"style":1},"3":{"style":1}},"69":{"2":{"style":1},"3":{"style":1}},"13":{"5":{"style":1},"2":{"style":1},"9":{"style":1},"6":{"style":1},"3":{"style":1},"7":{"style":1},"4":{"style":1},"8":{"style":1}},"31":{"2":{"style":1},"3":{"style":1}},"48":{"2":{"style":1},"3":{"style":1}},"66":{"2":{"style":1},"3":{"style":1}},"9":{"5":{"style":1},"2":{"style":3},"6":{"style":1},"3":{"style":1},"7":{"style":1},"4":{"style":1},"8":{"style":1}},"45":{"2":{"rawvalue":"<object width=\"560\" height=\"340\"><param name=\"movie\" value=\"http://www.youtube.com/v/XTIsqtEojFE&hl=en_GB&fs=1&rel=0\"></param><param name=\"allowFullScreen\" value=\"true\"></param><param name=\"allowscriptaccess\" value=\"always\"></param><embed src=\"http://www.youtube.com/v/XTIsqtEojFE&hl=en_GB&fs=1&rel=0\" type=\"application/x-shockwave-flash\" allowscriptaccess=\"always\" allowfullscreen=\"true\" width=\"560\" height=\"340\"></embed></object>","formula":"<object width=\"560\" height=\"340\"><param name=\"movie\" value=\"http://www.youtube.com/v/XTIsqtEojFE&hl=en_GB&fs=1&rel=0\"></param><param name=\"allowFullScreen\" value=\"true\"></param><param name=\"allowscriptaccess\" value=\"always\"></param><embed src=\"http://www.youtube.com/v/XTIsqtEojFE&hl=en_GB&fs=1&rel=0\" type=\"application/x-shockwave-flash\" allowscriptaccess=\"always\" allowfullscreen=\"true\" width=\"560\" height=\"340\"></embed></object>","merge":{"right":7,"down":15},"parents":"bleh","value":"<object width=\"560\" height=\"340\"><param name=\"movie\" value=\"http://www.youtube.com/v/XTIsqtEojFE&hl=en_GB&fs=1&rel=0\"></param><param name=\"allowFullScreen\" value=\"true\"></param><param name=\"allowscriptaccess\" value=\"always\"></param><embed src=\"http://www.youtube.com/v/XTIsqtEojFE&hl=en_GB&fs=1&rel=0\" type=\"application/x-shockwave-flash\" allowscriptaccess=\"always\" allowfullscreen=\"true\" width=\"560\" height=\"340\"></embed></object>","style":1,"overwrite-color":"auto"},"3":{"style":1}},"63":{"2":{"style":1},"3":{"style":1}},"10":{"5":{"style":1},"2":{"rawvalue":"&nbsp;Get detailed help at&nbsp;<a href=\"http://support.hypernumbers.com/\"></a><a href=\"http://support.hypernumbers.com/\">our support site</a> or watch these short getting started videos.<a href=\"http://support.hypernumbers.com/\"></a><a href=\"http://support.hypernumbers.com/\"></a>","formula":"&nbsp;Get detailed help at&nbsp;<a href=\"http://support.hypernumbers.com/\"></a><a href=\"http://support.hypernumbers.com/\">our support site</a> or watch these short getting started videos.<a href=\"http://support.hypernumbers.com/\"></a><a href=\"http://support.hypernumbers.com/\"></a>","merge":{"right":7,"down":0},"parents":"bleh","value":"&nbsp;Get detailed help at&nbsp;<a href=\"http://support.hypernumbers.com/\"></a><a href=\"http://support.hypernumbers.com/\">our support site</a> or watch these short getting started videos.<a href=\"http://support.hypernumbers.com/\"></a><a href=\"http://support.hypernumbers.com/\"></a>","style":1,"overwrite-color":"auto"},"9":{"style":1},"6":{"style":1},"3":{"style":1},"7":{"style":1},"4":{"style":1},"8":{"style":1}},"24":{"5":{"style":1},"2":{"style":1},"9":{"style":1},"6":{"style":1},"3":{"style":1},"7":{"style":1},"4":{"style":1},"8":{"style":1}},"42":{"2":{"style":1},"3":{"style":1}},"59":{"2":{"style":1},"3":{"style":1}},"21":{"5":{"style":1},"2":{"style":1},"9":{"style":1},"6":{"style":1},"3":{"style":1},"7":{"style":1},"4":{"style":1},"8":{"style":1}},"38":{"2":{"style":1},"3":{"style":1}},"56":{"2":{"style":1},"3":{"style":1}},"74":{"2":{"style":1},"3":{"style":1}},"17":{"5":{"style":1},"2":{"style":1},"9":{"style":1},"6":{"style":1},"3":{"style":1},"7":{"style":1},"4":{"style":1},"8":{"style":1}},"35":{"2":{"style":1},"3":{"style":1}},"53":{"2":{"style":1},"3":{"style":1}},"71":{"2":{"style":1},"3":{"style":1}},"14":{"5":{"style":1},"2":{"style":1},"9":{"style":1},"6":{"style":1},"3":{"style":1},"7":{"style":1},"4":{"style":1},"8":{"style":1}},"32":{"2":{"style":1},"3":{"style":1}},"50":{"2":{"style":1},"3":{"style":1}},"49":{"2":{"style":1},"3":{"style":1}},"67":{"2":{"style":1},"3":{"style":1}},"11":{"5":{"style":1},"2":{"rawvalue":"<object width=\"560\" height=\"340\"><param name=\"movie\" value=\"http://www.youtube.com/v/F6WpsmziMBQ&amp;hl=en_GB&amp;fs=1&amp;rel=0\"><param name=\"allowFullScreen\" value=\"true\"><param name=\"allowscriptaccess\" value=\"always\"><embed src=\"http://www.youtube.com/v/F6WpsmziMBQ&amp;hl=en_GB&amp;fs=1&amp;rel=0\" type=\"application/x-shockwave-flash\" allowscriptaccess=\"always\" allowfullscreen=\"true\" width=\"560\" height=\"340\"></object>","formula":"<object width=\"560\" height=\"340\"><param name=\"movie\" value=\"http://www.youtube.com/v/F6WpsmziMBQ&amp;hl=en_GB&amp;fs=1&amp;rel=0\"><param name=\"allowFullScreen\" value=\"true\"><param name=\"allowscriptaccess\" value=\"always\"><embed src=\"http://www.youtube.com/v/F6WpsmziMBQ&amp;hl=en_GB&amp;fs=1&amp;rel=0\" type=\"application/x-shockwave-flash\" allowscriptaccess=\"always\" allowfullscreen=\"true\" width=\"560\" height=\"340\"></object>","merge":{"right":7,"down":15},"parents":"bleh","value":"<object width=\"560\" height=\"340\"><param name=\"movie\" value=\"http://www.youtube.com/v/F6WpsmziMBQ&amp;hl=en_GB&amp;fs=1&amp;rel=0\"><param name=\"allowFullScreen\" value=\"true\"><param name=\"allowscriptaccess\" value=\"always\"><embed src=\"http://www.youtube.com/v/F6WpsmziMBQ&amp;hl=en_GB&amp;fs=1&amp;rel=0\" type=\"application/x-shockwave-flash\" allowscriptaccess=\"always\" allowfullscreen=\"true\" width=\"560\" height=\"340\"></object>","style":1,"overwrite-color":"auto"},"9":{"style":1},"6":{"style":1},"3":{"style":1},"7":{"style":1},"4":{"style":1},"8":{"style":1}},"28":{"2":{"rawvalue":"<object width=\"560\" height=\"340\"><param name=\"movie\" value=\"http://www.youtube.com/v/SapYOc-POzU&hl=en_GB&fs=1&rel=0\"></param><param name=\"allowFullScreen\" value=\"true\"></param><param name=\"allowscriptaccess\" value=\"always\"></param><embed src=\"http://www.youtube.com/v/SapYOc-POzU&hl=en_GB&fs=1&rel=0\" type=\"application/x-shockwave-flash\" allowscriptaccess=\"always\" allowfullscreen=\"true\" width=\"560\" height=\"340\"></embed></object>","formula":"<object width=\"560\" height=\"340\"><param name=\"movie\" value=\"http://www.youtube.com/v/SapYOc-POzU&hl=en_GB&fs=1&rel=0\"></param><param name=\"allowFullScreen\" value=\"true\"></param><param name=\"allowscriptaccess\" value=\"always\"></param><embed src=\"http://www.youtube.com/v/SapYOc-POzU&hl=en_GB&fs=1&rel=0\" type=\"application/x-shockwave-flash\" allowscriptaccess=\"always\" allowfullscreen=\"true\" width=\"560\" height=\"340\"></embed></object>","merge":{"right":7,"down":15},"parents":"bleh","value":"<object width=\"560\" height=\"340\"><param name=\"movie\" value=\"http://www.youtube.com/v/SapYOc-POzU&hl=en_GB&fs=1&rel=0\"></param><param name=\"allowFullScreen\" value=\"true\"></param><param name=\"allowscriptaccess\" value=\"always\"></param><embed src=\"http://www.youtube.com/v/SapYOc-POzU&hl=en_GB&fs=1&rel=0\" type=\"application/x-shockwave-flash\" allowscriptaccess=\"always\" allowfullscreen=\"true\" width=\"560\" height=\"340\"></embed></object>","style":1,"overwrite-color":"auto"},"3":{"style":1}},"46":{"2":{"style":1},"3":{"style":1}},"64":{"2":{"style":1},"3":{"style":1}},"25":{"5":{"style":1},"2":{"style":1},"9":{"style":1},"6":{"style":1},"3":{"style":1},"7":{"style":1},"4":{"style":1},"8":{"style":1}},"22":{"5":{"style":1},"2":{"style":1},"9":{"style":1},"6":{"style":1},"3":{"style":1},"7":{"style":1},"4":{"style":1},"8":{"style":1}},"40":{"2":{"style":1},"3":{"style":1}},"39":{"2":{"style":1},"3":{"style":1}},"57":{"2":{"style":1},"3":{"style":1}},"75":{"2":{"style":1},"3":{"style":1}},"18":{"5":{"style":1},"2":{"style":1},"9":{"style":1},"6":{"style":1},"3":{"style":1},"7":{"style":1},"4":{"style":1},"8":{"style":1}},"36":{"2":{"style":1},"3":{"style":1}},"54":{"2":{"style":1},"3":{"style":1}},"72":{"2":{"style":1},"3":{"style":1}},"15":{"5":{"style":1},"2":{"style":1},"9":{"style":1},"6":{"style":1},"3":{"style":1},"7":{"style":1},"4":{"style":1},"8":{"style":1}},"33":{"2":{"style":1},"3":{"style":1}},"51":{"2":{"style":1},"3":{"style":1}},"68":{"2":{"style":1},"3":{"style":1}},"12":{"5":{"style":1},"2":{"style":1},"9":{"style":1},"6":{"style":1},"3":{"style":1},"7":{"style":1},"4":{"style":1},"8":{"style":1}},"30":{"2":{"style":1},"3":{"style":1}},"29":{"2":{"style":1},"3":{"style":1}},"47":{"2":{"style":1},"3":{"style":1}},"65":{"2":{"style":1},"3":{"style":1}},"26":{"5":{"style":1},"2":{"style":1},"9":{"style":1},"6":{"style":1},"3":{"style":1},"7":{"style":1},"4":{"style":1},"8":{"style":1}},"8":{"5":{"style":1},"2":{"rawvalue":"Watch The Getting Started Videos!","formula":"Watch The Getting Started Videos!","merge":{"right":7,"down":1},"parents":"bleh","value":"Watch The Getting Started Videos!","style":3,"overwrite-color":"auto"},"6":{"style":1},"3":{"style":1},"7":{"style":1},"4":{"style":1},"8":{"style":1}},"62":{"2":{"rawvalue":"<object width=\"560\" height=\"340\"><param name=\"movie\" value=\"http://www.youtube.com/v/MAl9OAICDWo&hl=en_GB&fs=1&rel=0\"></param><param name=\"allowFullScreen\" value=\"true\"></param><param name=\"allowscriptaccess\" value=\"always\"></param><embed src=\"http://www.youtube.com/v/MAl9OAICDWo&hl=en_GB&fs=1&rel=0\" type=\"application/x-shockwave-flash\" allowscriptaccess=\"always\" allowfullscreen=\"true\" width=\"560\" height=\"340\"></embed></object>","formula":"<object width=\"560\" height=\"340\"><param name=\"movie\" value=\"http://www.youtube.com/v/MAl9OAICDWo&hl=en_GB&fs=1&rel=0\"></param><param name=\"allowFullScreen\" value=\"true\"></param><param name=\"allowscriptaccess\" value=\"always\"></param><embed src=\"http://www.youtube.com/v/MAl9OAICDWo&hl=en_GB&fs=1&rel=0\" type=\"application/x-shockwave-flash\" allowscriptaccess=\"always\" allowfullscreen=\"true\" width=\"560\" height=\"340\"></embed></object>","merge":{"right":7,"down":15},"parents":"bleh","value":"<object width=\"560\" height=\"340\"><param name=\"movie\" value=\"http://www.youtube.com/v/MAl9OAICDWo&hl=en_GB&fs=1&rel=0\"></param><param name=\"allowFullScreen\" value=\"true\"></param><param name=\"allowscriptaccess\" value=\"always\"></param><embed src=\"http://www.youtube.com/v/MAl9OAICDWo&hl=en_GB&fs=1&rel=0\" type=\"application/x-shockwave-flash\" allowscriptaccess=\"always\" allowfullscreen=\"true\" width=\"560\" height=\"340\"></embed></object>","style":1,"overwrite-color":"auto"},"3":{"style":1}}}}