{"time":1334261839479115,"user":"anonymous","host":"http://rb78.tiny.hn:80","permissions":{"champion":"spreadsheet","challenger":[],"views":{"spreadsheet":{"everyone":false,"groups":["admin"]},"table":{"everyone":false,"groups":["admin"]},"webpage":{"everyone":false,"groups":["admin"]},"wikipage":{"everyone":false,"groups":["admin"]}}},"views":[],"page":{},"styles":{"1334101168001573":"color:#000;background-color:#66EEFF;font-weight:bold;font-size:100%;font-family:tahoma, sans-serif;text-align:left;","1334105090277946":"color:#000;background-color:#00D6DD;text-align:left;","1334104287065661":"color:#000000;background-color:#00D6DD;text-align:right;","1333228655591400":"color:#FFF;background-color:#080808;","1333228655660624":"color:#FFF;background-color:#080808;font-weight:bold;font-size:160%;","1334008176255546":"font-weight:normal;","1334102478862004":"color:#000;background-color:#EEEE11;font-weight:bold;text-align:left;","1334249723918968":"font-size:100%;text-align:left;","1334186545443646":"font-weight:bold;font-size:100%;text-align:center;","1334105297179915":"color:#000;font-weight:normal;","1334182858130870":"color:#000;background-color:#eeee11;font-weight:bold;text-align:left;","1333228655672966":"color:#FFF;font-weight:bold;font-size:160%;text-align:left;","1332329067325415":"color:#000;font-weight:bold;font-size:220%;","1334105297179783":"color:#000;background-color:#66EEFF;font-weight:normal;text-align:left;","1334156571176678":"color:#FFF;text-align:right;","1334249220680776":"color:#000;background-color:#bbbbbb;text-align:left;","1334101173376141":"color:#000;background-color:#66EEFF;font-weight:normal;font-size:100%;font-family:tahoma, sans-serif;text-align:left;","1333228655660283":"color:#FFF;font-weight:bold;font-size:160%;","1334256696238642":"font-size:100%;font-family:Helvetica, Arial, serif;text-align:center;","1332338068500662":"font-size:90%;","1334009826449896":"font-weight:bold;font-family:sans-serif;text-align:center;","1334105110412538":"color:#000;background-color:#00D6DD;font-weight:bold;text-align:left;","1334156571179154":"color:#FFF;background-color:#0011CC;text-align:left;","1334099651998605":"color:#000;background-color:#00DD00;font-weight:bold;font-size:220%;text-align:left;","1333228655603264":"color:#FFF;background-color:#080808;font-weight:bold;text-align:left;","1334156575343641":"color:#FFF;background-color:#0011CC;font-weight:bold;","1334009176831980":"font-weight:normal;text-align:right;","1334090037014385":"color:#000;background-color:#66EEFF;text-align:left;","1334105297179991":"color:#000;background-color:#66EEFF;font-weight:normal;","1334010502704921":"font-weight:bold;font-size:140%;font-family:sans-serif;text-align:left;","1334158206859559":"color:#000;background-color:#FFFFFF;text-align:left;","1332329067325546":"color:#000;background-color:#FFFF00;font-weight:bold;font-size:220%;","1333228655603068":"color:#FFF;font-weight:bold;text-align:left;","1332329067320122":"color:#000;","1332329067329087":"color:#000;font-weight:bold;font-size:220%;text-align:left;","1334104382982318":"color:#000000;background-color:#00D6DD;font-weight:bold;","1334184349727702":"color:#000;background-color:#eeee11;font-weight:bold;","1334256692345753":"font-size:100%;font-family:Helvetica, Arial, serif;","1334254908641209":"color:#000000;font-weight:bold;","1334102478860232":"color:#000;background-color:#EEEE11;","1334090079102308":"color:#000;font-weight:bold;font-size:140%;font-family:sans-serif;text-align:left;","1334254981985806":"color:#000000;background-color:#eeee11;","1332335628310031":"text-align:center;","1334099977707747":"color:#000;background-color:#66EEFF;","1334261002521697":"color:#000;background-color:bbbbbb;","1334105090277495":"color:#000;background-color:#00D6DD;","1334167306886831":"color:#000;background-color:#EEEE11;font-weight:bold;","1334104287060963":"color:#000000;background-color:#00D6DD;text-align:left;","1334009764747023":"font-weight:normal;text-align:center;","1334157380013355":"font-weight:bold;font-size:140%;text-align:center;","1332329067329218":"color:#000;background-color:#FFFF00;font-weight:bold;font-size:220%;text-align:left;","1334156575343929":"color:#FFF;background-color:#0011CC;font-weight:bold;text-align:left;","1332329154502642":"font-weight:bold;font-size:160%;","1333455646024885":"font-weight:bold;font-size:140%;text-align:left;","1333228655673311":"color:#FFF;background-color:#080808;font-weight:bold;font-size:160%;text-align:left;","1333228655678070":"color:#FFF;background-color:#080808;font-size:90%;text-align:left;","1334102470868554":"color:#000;background-color:#EEEE11;text-align:left;","1334104287067827":"color:#000000;font-weight:bold;text-align:left;","1334009228308175":"font-weight:bold;text-align:right;","1332329045541968":"font-weight:bold;","1334256674929708":"font-size:140%;font-family:Helvetica, Arial, serif;","1334009830635659":"font-weight:normal;font-family:sans-serif;text-align:center;","1334255340059063":"color:#000;background-color:#FFFFFF;font-weight:bold;","1334105110412630":"color:#000;background-color:#66EEFF;font-weight:bold;text-align:left;","1334090079102368":"color:#000;background-color:#66EEFF;font-weight:bold;font-size:140%;font-family:sans-serif;text-align:left;","1334101179929219":"color:#000;background-color:#66EEFF;font-weight:normal;font-size:100%;font-family:sans-serif;text-align:left;","1334105064449279":"color:#000;font-weight:bold;text-align:center;","1334105064449366":"color:#000;background-color:#BBBBBB;font-weight:bold;text-align:center;","1334104287065530":"color:#000000;text-align:right;","1333228655677717":"color:#FFF;font-size:90%;text-align:left;","1334158079962138":"color:#000;background-color:#FFFFFF;","1334104287059513":"color:#000000;","1334104287059641":"color:#000000;background-color:#00D6DD;","1334105064448102":"color:#000;background-color:#BBBBBB;","1334255484387228":"color:#000000;background-color:#FFFFFF;text-align:left;","1334255484386288":"color:#000000;background-color:#FFFFFF;","1334101944942872":"font-weight:bold;font-size:100%;text-align:left;","1334105297179717":"color:#000;font-weight:normal;text-align:left;","1332328896967086":"text-align:left;","1333228655633550":"color:#FFF;background-color:#080808;font-weight:bold;","1334156571178899":"color:#FFF;background-color:#0011CC;","1334187948180955":"text-align:null;","1334188489173353":"font-weight:bold;font-size:100%;","1334170782081926":"color:#000;background-color:#eeee11;","1333228655650877":"color:#FFF;background-color:#080808;text-align:left;","1334008074883204":"font-weight:bold;text-align:center;","1334102478861931":"color:#000;font-weight:bold;text-align:left;","1332329045542997":"font-weight:bold;text-align:left;","1333228655650566":"color:#FFF;text-align:left;","1333455797939787":"font-size:140%;","1334157380012613":"font-weight:bold;font-size:140%;","1334177238139836":"color:#000;background-color:#66EEFF;font-weight:normal;font-size:null;font-family:sans-serif;text-align:center;","1334249701825488":"color:#000000;background-color:#00D6DD;font-family:sans-serif;text-align:left;","1334008176255405":"font-weight:normal;text-align:left;","1332330873806253":"text-align:right;","1334156571176756":"color:#FFF;background-color:#0011CC;text-align:right;","1334177210666596":"color:#000;background-color:#FFFFFF;font-weight:bold;text-align:left;","1334255484394210":"color:#000000;background-color:#FFFFFF;font-weight:bold;","1334258757653522":"color:#000;background-color:#FFFFFF;font-weight:bold;text-align:center;","1334158394908308":"font-size:140%;text-align:center;","1334170782082689":"color:#000;background-color:#eeee11;text-align:left;","1334101120715045":"color:#000;background-color:#66EEFF;font-weight:bold;font-size:100%;font-family:sans-serif;text-align:left;","1332329048693237":"font-weight:bold;font-size:220%;text-align:left;","1332329048692057":"font-weight:bold;font-size:220%;","1334249709407898":"color:#000000;background-color:#00D6DD;font-family:Helvetica, Arial, serif;text-align:left;","1334156575341467":"color:#FFF;background-color:#0011CC;font-weight:bold;text-align:right;","1334256672394798":"font-family:Helvetica, Arial, serif;","1332329154504007":"font-weight:bold;font-size:160%;text-align:left;","1332335659317969":"font-size:90%;text-align:left;","1333228655633257":"color:#FFF;font-weight:bold;","1333228655591198":"color:#FFF;","1334105110412343":"color:#000;background-color:#66EEFF;font-weight:bold;","1334089782989006":"color:#000;background-color:#BBBBBB;text-align:left;","1334101918319507":"font-size:140%;text-align:left;","1332329067320341":"color:#000;background-color:#FFFF00;","1334009840863122":"font-weight:bold;text-align:null;","1334010479874165":"font-weight:bold;font-size:140%;font-family:sans-serif;text-align:center;","1334089782988929":"color:#000;text-align:left;","1334104287067931":"color:#000000;background-color:#00D6DD;font-weight:bold;text-align:left;","1334101865050663":"font-size:140%;text-align:right;","1334104287060874":"color:#000000;text-align:left;","1334105110412262":"color:#000;background-color:#00D6DD;font-weight:bold;","1334101132615863":"color:#000;background-color:#66EEFF;font-weight:bold;font-size:100%;font-family:monospace;text-align:left;","1334258434247099":"color:#000;font-weight:bold;","1334101186936978":"color:#000;background-color:#66EEFF;font-weight:normal;font-size:null;font-family:sans-serif;text-align:left;"},"row":{},"column":{},"cell":{"5":{"2":{"formula":"AppLean Create Assumption","merge":{"right":4,"down":1},"value":"AppLean Create Assumption","style":1332329154504007,"overwrite-color":"auto"},"14":{"formula":"=LINK(\"../../l1_dashboard/\",\"Go To Dashboard\")","merge":{"right":0,"down":1},"value":"<a href='../../l1_dashboard/'>Go To Dashboard</a>","style":1334008074883204,"overwrite-color":"auto"}},"23":{"5":{"style":1334170782081926},"2":{"style":1334184349727702},"9":{"style":1334170782081926},"10":{"style":1334170782081926},"6":{"style":1334170782081926},"3":{"style":1334170782081926},"11":{"style":1334170782081926},"7":{"style":1334170782081926},"4":{"style":1334170782081926},"8":{"style":1334170782081926}},"41":{"5":{"formula":"","value":"","style":1334104287060963,"overwrite-color":"auto"},"2":{"formula":"","value":"","style":1334104287060963,"overwrite-color":"auto"},"6":{"formula":"","value":"","style":1334104287060963,"overwrite-color":"auto"},"3":{"formula":"","value":"","style":1334104287060963,"overwrite-color":"auto"},"7":{"style":1334104287059641},"4":{"formula":"","value":"","style":1334104287060963,"overwrite-color":"auto"}},"20":{"5":{"style":1334170782081926},"2":{"style":1334184349727702},"10":{"style":1334170782081926},"9":{"style":1334170782081926},"6":{"style":1334170782081926},"3":{"style":1334170782081926},"11":{"style":1334170782081926},"7":{"style":1334170782081926},"4":{"style":1334170782081926},"8":{"style":1334170782081926}},"2":{"2":{"formula":"","value":"","style":1332328896967086,"overwrite-color":"auto"}},"19":{"5":{"style":1334170782081926},"2":{"style":1334184349727702},"10":{"style":1334170782081926},"9":{"style":1334170782081926},"6":{"style":1334170782081926},"3":{"style":1334170782081926},"11":{"style":1334170782081926},"7":{"style":1334170782081926},"4":{"style":1334170782081926},"8":{"style":1334170782081926}},"37":{"5":{"formula":"","value":"","style":1334104287060963,"overwrite-color":"auto"},"2":{"formula":"","value":"","style":1334104382982318,"overwrite-color":"auto"},"6":{"formula":"","value":"","style":1334104287060963,"overwrite-color":"auto"},"3":{"formula":"","value":"","style":1334104287060963,"overwrite-color":"auto"},"7":{"style":1334104287059641},"4":{"formula":"Complementary Product 2","merge":{"right":7,"down":0},"value":"Complementary Product 2","style":1334104287060963,"overwrite-color":"auto","input":"inline"}},"34":{"5":{"formula":"","value":"","style":1334104287060963,"overwrite-color":"auto","input":"inline"},"2":{"formula":"","value":"","style":1334104382982318,"overwrite-color":"auto"},"9":{"input":"inline"},"10":{"input":"inline"},"6":{"formula":"","value":"","style":1334104287060963,"overwrite-color":"auto","input":"inline"},"3":{"formula":"","value":"","style":1334104287060963,"overwrite-color":"auto"},"11":{"input":"inline"},"7":{"style":1334104287059641,"input":"inline"},"4":{"formula":"","value":"","style":1334104287060963,"overwrite-color":"auto","input":"inline"},"8":{"style":1334104287059641,"input":"inline"}},"16":{"5":{"style":1334170782081926},"2":{"formula":"Solution Hypothesis","merge":{"right":1,"down":0},"value":"Solution Hypothesis","style":1334182858130870,"overwrite-color":"auto"},"9":{"style":1334170782081926},"6":{"style":1334170782081926},"3":{"style":1334170782081926},"7":{"style":1334170782081926},"4":{"formula":"=T(../prob_work/D26)","merge":{"right":7,"down":0},"value":"this is another solution statement","style":1334170782082689,"overwrite-color":"auto"},"8":{"style":1334170782081926}},"13":{"2":{"formula":"","value":"","style":1332328896967086,"overwrite-color":"auto"}},"48":{"5":{"formula":"","value":"","style":1332328896967086,"overwrite-color":"auto"},"2":{"formula":"","value":"","style":1332328896967086,"overwrite-color":"auto"},"6":{"formula":"","value":"","style":1332328896967086,"overwrite-color":"auto"},"3":{"formula":"","value":"","style":1332328896967086,"overwrite-color":"auto"},"4":{"formula":"","value":"","style":1332328896967086,"overwrite-color":"auto"}},"31":{"5":{"formula":"","value":"","style":1334104287060963,"overwrite-color":"auto","input":"inline"},"2":{"formula":"","value":"","style":1334104382982318,"overwrite-color":"auto"},"10":{"input":"inline"},"9":{"input":"inline"},"6":{"formula":"","value":"","style":1334104287060963,"overwrite-color":"auto","input":"inline"},"3":{"formula":"","value":"","style":1334104287060963,"overwrite-color":"auto"},"11":{"input":"inline"},"7":{"style":1334104287059641,"input":"inline"},"4":{"formula":"","value":"","style":1334104287060963,"overwrite-color":"auto","input":"inline"},"8":{"style":1334104287059641,"input":"inline"}},"10":{"2":{"formula":"Instructions needed for Comps","merge":{"right":10,"down":4},"value":"Instructions needed for Comps","style":1332328896967086,"overwrite-color":"auto"}},"45":{"5":{"formula":"","value":"","style":1332328896967086,"overwrite-color":"auto"},"2":{"formula":"","value":"","style":1332328896967086,"overwrite-color":"auto"},"6":{"formula":"","value":"","style":1332328896967086,"overwrite-color":"auto"},"3":{"formula":"","value":"","style":1332328896967086,"overwrite-color":"auto"},"4":{"formula":"","value":"","style":1332328896967086,"overwrite-color":"auto"}},"9":{"2":{"formula":"Instructions","merge":{"right":12,"down":0},"value":"Instructions","style":1334008074883204,"overwrite-color":"auto"}},"27":{"5":{"style":1334104287059641},"2":{"style":1334104287059641},"9":{"style":1334104287059641},"10":{"style":1334104287059641},"6":{"style":1334104287059641},"3":{"style":1334104287059641},"11":{"style":1334104287059641},"7":{"style":1334104287059641},"4":{"style":1334104287059641},"8":{"style":1334104287059641}},"6":{"2":{"formula":"","value":"","style":1332329154502642,"overwrite-color":"auto"},"14":{"style":1334008074883204}},"24":{"5":{"style":1334170782081926},"2":{"style":1334170782081926},"9":{"style":1334170782081926},"10":{"style":1334170782081926},"6":{"style":1334170782081926},"3":{"style":1334170782081926},"11":{"style":1334170782081926},"7":{"style":1334170782081926},"4":{"style":1334170782081926},"8":{"style":1334170782081926}},"42":{"5":{"formula":"","value":"","style":1334104287060963,"overwrite-color":"auto"},"2":{"formula":"","value":"","style":1334104287060963,"overwrite-color":"auto"},"6":{"formula":"","value":"","style":1334104287060963,"overwrite-color":"auto"},"3":{"formula":"","value":"","style":1334104287060963,"overwrite-color":"auto"},"7":{"style":1334104287059641},"4":{"formula":"","value":"","style":1334104287060963,"overwrite-color":"auto"}},"3":{"2":{"formula":"","value":"","style":1332328896967086,"overwrite-color":"auto"}},"38":{"5":{"formula":"","value":"","style":1334104287060963,"overwrite-color":"auto"},"2":{"formula":"Observations","value":"Observations","style":1334104287067931,"overwrite-color":"auto"},"6":{"formula":"","value":"","style":1334104287060963,"overwrite-color":"auto"},"3":{"formula":"","value":"","style":1334104287060963,"overwrite-color":"auto"},"7":{"style":1334104287059641},"4":{"formula":"Complementary Observations","merge":{"right":7,"down":4},"value":"Complementary Observations","style":1334104287060963,"overwrite-color":"auto","input":"inline"}},"21":{"5":{"style":1334170782081926},"2":{"style":1334184349727702},"9":{"style":1334170782081926},"10":{"style":1334170782081926},"6":{"style":1334170782081926},"3":{"style":1334170782081926},"11":{"style":1334170782081926},"7":{"style":1334170782081926},"4":{"style":1334170782081926},"8":{"style":1334170782081926}},"35":{"5":{"formula":"","value":"","style":1334104287060963,"overwrite-color":"auto"},"2":{"formula":"","value":"","style":1334104382982318,"overwrite-color":"auto"},"9":{"style":1334104287059641},"10":{"style":1334104287059641},"6":{"formula":"","value":"","style":1334104287060963,"overwrite-color":"auto"},"3":{"formula":"","value":"","style":1334104287060963,"overwrite-color":"auto"},"11":{"style":1334104287059641},"7":{"style":1334104287059641},"4":{"formula":"","value":"","style":1334104287060963,"overwrite-color":"auto"},"8":{"style":1334104287059641}},"17":{"5":{"style":1334170782081926},"2":{"formula":"Assumption","value":"Assumption","style":1334182858130870,"overwrite-color":"auto"},"9":{"style":1334170782081926},"10":{"style":1334170782081926},"6":{"style":1334170782081926},"3":{"style":1334170782081926},"11":{"style":1334170782081926},"7":{"style":1334170782081926},"4":{"formula":"=ZTABLE.8X5({\"Assumption\",\"Risk Priority\"},../[true]/[true]/c20:C21)","merge":{"right":7,"down":4},"value":"<table id='tbl_7e5f1995d172ce11' class='tablesorter'><thead><tr><th>Links</th><th>Assumption</th><th>Risk Priority</th></tr></thead><tr><td><a href=\"/students/0000005/l1_dashboard/prob_work/_replies/\">Link</a></td><td></td><td></td></tr><tr><td><a href=\"/students/0000005/l1_dashboard/prob_work/assump_work/\">Link</a></td><td>this is a betyter assumty</td><td><select class='hninput' data-name='default' data-label='Priority' ><option>1</option><option>2</option><option>3</option><option>4</option><option>5</option></select></td></tr><tr><td><a href=\"/students/0000005/l1_dashboard/assump_work_0000002/research/\">Link</a></td><td></td><td></td></tr></table>","preview":{"txt":"ZTable ","h":5,"w":8},"style":1334170782082689,"overwrite-color":"auto"},"8":{"style":1334170782081926}},"32":{"5":{"formula":"","value":"","style":1334104287060963,"overwrite-color":"auto","input":"inline"},"2":{"formula":"","value":"","style":1334104382982318,"overwrite-color":"auto"},"9":{"input":"inline"},"10":{"input":"inline"},"6":{"formula":"","value":"","style":1334104287060963,"overwrite-color":"auto","input":"inline"},"3":{"formula":"","value":"","style":1334104287060963,"overwrite-color":"auto"},"11":{"input":"inline"},"7":{"style":1334104287059641,"input":"inline"},"4":{"formula":"","value":"","style":1334104287060963,"overwrite-color":"auto","input":"inline"},"8":{"style":1334104287059641,"input":"inline"}},"49":{"5":{"formula":"","value":"","style":1332328896967086,"overwrite-color":"auto"},"2":{"formula":"","value":"","style":1332328896967086,"overwrite-color":"auto"},"6":{"formula":"","value":"","style":1332328896967086,"overwrite-color":"auto"},"3":{"formula":"","value":"","style":1332328896967086,"overwrite-color":"auto"},"4":{"formula":"","value":"","style":1332328896967086,"overwrite-color":"auto"}},"14":{"2":{"formula":"","value":"","style":1332328896967086,"overwrite-color":"auto"}},"11":{"2":{"formula":"","value":"","style":1332328896967086,"overwrite-color":"auto"}},"46":{"5":{"formula":"","value":"","style":1332328896967086,"overwrite-color":"auto"},"2":{"formula":"","value":"","style":1332328896967086,"overwrite-color":"auto"},"6":{"formula":"","value":"","style":1332328896967086,"overwrite-color":"auto"},"3":{"formula":"","value":"","style":1332328896967086,"overwrite-color":"auto"},"4":{"formula":"","value":"","style":1332328896967086,"overwrite-color":"auto"}},"28":{"5":{"formula":"","value":"","style":1334104287060963,"overwrite-color":"auto"},"2":{"formula":"Competitive &nbsp; &nbsp; &nbsp; &nbsp; Products / Services","merge":{"right":1,"down":1},"value":"Competitive &nbsp; &nbsp; &nbsp; &nbsp; Products / Services","style":1334104287067931,"overwrite-color":"auto"},"6":{"formula":"","value":"","style":1334104287060963,"overwrite-color":"auto"},"3":{"formula":"","value":"","style":1334104287060963,"overwrite-color":"auto"},"7":{"style":1334104287059641},"4":{"formula":"Competitive Product 1","merge":{"right":7,"down":0},"value":"Competitive Product 1","style":1334104287060963,"overwrite-color":"auto","input":"inline"},"8":{"style":1334104287059641}},"7":{"5":{"style":1334170782081926},"2":{"formula":"Project Name","merge":{"right":1,"down":0},"value":"Project Name","style":1332329045542997,"overwrite-color":"auto"},"10":{"style":1334170782081926},"9":{"style":1334170782081926},"6":{"style":1334170782081926},"11":{"style":1334170782081926},"7":{"style":1334170782081926},"4":{"formula":"=t(../../C9)\u00a0","merge":{"right":5,"down":0},"value":"My Project","style":1334170782082689,"overwrite-color":"auto"},"12":{"style":1334170782081926},"8":{"style":1334170782081926}},"43":{"5":{"formula":"","value":"","style":1334158206859559,"overwrite-color":"auto"},"2":{"formula":"","value":"","style":1334158206859559,"overwrite-color":"auto"},"9":{"style":1334158079962138},"10":{"style":1334158079962138},"6":{"formula":"","value":"","style":1334158206859559,"overwrite-color":"auto"},"3":{"formula":"","value":"","style":1334158206859559,"overwrite-color":"auto"},"11":{"style":1334158079962138},"7":{"style":1334158079962138},"4":{"formula":"","value":"","style":1334158206859559,"overwrite-color":"auto"},"8":{"style":1334158079962138}},"25":{"5":{"style":1334170782081926},"2":{"style":1334170782081926},"10":{"style":1334170782081926},"9":{"style":1334170782081926},"6":{"style":1334170782081926},"3":{"style":1334170782081926},"11":{"style":1334170782081926},"7":{"style":1334170782081926},"4":{"style":1334170782081926},"8":{"style":1334170782081926}},"4":{"2":{"formula":"=CRUMB.TRAIL()","merge":{"right":9,"down":0},"value":"<a href=\"/\">http://rb78.tiny.hn:80</a> -> <a href=\"/students/\">students</a> -> <a href=\"/students/0000005/\">0000005</a> -> <a href=\"/students/0000005/l1_dashboard/\">l1_dashboard</a> -> <a href=\"/students/0000005/l1_dashboard/comps/\">comps</a>","style":1332335659317969,"overwrite-color":"auto"}},"22":{"5":{"style":1334170782081926},"2":{"formula":"Search Results and Summation","merge":{"right":1,"down":1},"value":"Search Results and Summation","style":1334182858130870,"overwrite-color":"auto"},"9":{"style":1334170782081926},"10":{"style":1334170782081926},"6":{"style":1334170782081926},"3":{"style":1334170782081926},"11":{"style":1334170782081926},"7":{"style":1334170782081926},"4":{"formula":"=ZTABLE.8X5({\"Target\",\"Results\"},../[true]/[true]/c18:C19)","merge":{"right":7,"down":4},"value":"<table id='tbl_f7d2fdca948ba8c5' class='tablesorter'><thead><tr><th>Links</th><th>Target</th><th>Results</th></tr></thead><tr><td><a href=\"/students/0000005/l1_dashboard/prob_work/_replies/\">Link</a></td><td></td><td></td></tr><tr><td><a href=\"/students/0000005/l1_dashboard/prob_work/assump_work/\">Link</a></td><td></td><td>#VALUE!</td></tr><tr><td><a href=\"/students/0000005/l1_dashboard/assump_work_0000002/research/\">Link</a></td><td>now is the time for all good men</td><td>to come to the aid of their country.</td></tr></table>","preview":{"txt":"ZTable ","h":5,"w":8},"style":1334170782082689,"overwrite-color":"auto"},"8":{"style":1334170782081926}},"40":{"5":{"formula":"","value":"","style":1334104287060963,"overwrite-color":"auto"},"2":{"formula":"","value":"","style":1334104287060963,"overwrite-color":"auto"},"6":{"formula":"","value":"","style":1334104287060963,"overwrite-color":"auto"},"3":{"formula":"","value":"","style":1334104287060963,"overwrite-color":"auto"},"7":{"style":1334104287059641},"4":{"formula":"","value":"","style":1334104287060963,"overwrite-color":"auto"}},"39":{"5":{"formula":"","value":"","style":1334104287060963,"overwrite-color":"auto"},"2":{"formula":"","value":"","style":1334104287060963,"overwrite-color":"auto"},"6":{"formula":"","value":"","style":1334104287060963,"overwrite-color":"auto"},"3":{"formula":"","value":"","style":1334104287060963,"overwrite-color":"auto"},"7":{"style":1334104287059641},"4":{"formula":"","value":"","style":1334104287060963,"overwrite-color":"auto"}},"1":{"2":{"formula":"=INCLUDE(/static-data/A5)","merge":{"right":14,"down":2},"value":"<div class='hn_inner' style='width:1200px;height:66px'><div data-ref='A5'style='left:0px;top:0px;width:1194px;height:64px;color:#000;background-color:#00DD00;font-weight:bold;font-size:220%;text-align:left;padding:1px 3px;'>Applied Lean</div></div>","preview":{"txt":"<div class='hn-include'>Including data from /static-data/A5:A5</div>","h":3,"w":15},"style":1334249723918968,"overwrite-color":"auto"}},"36":{"5":{"formula":"","value":"","style":1334104287060963,"overwrite-color":"auto","input":"inline"},"2":{"formula":"Complementary &nbsp; Products / Services","merge":{"right":1,"down":1},"value":"Complementary &nbsp; Products / Services","style":1334104287067931,"overwrite-color":"auto"},"10":{"style":1334104287059641,"input":"inline"},"9":{"style":1334104287059641,"input":"inline"},"6":{"formula":"","value":"","style":1334104287060963,"overwrite-color":"auto","input":"inline"},"3":{"formula":"","value":"","style":1334104287060963,"overwrite-color":"auto"},"11":{"style":1334104287059641,"input":"inline"},"7":{"style":1334104287059641,"input":"inline"},"4":{"formula":"Complementary Product 1","merge":{"right":7,"down":0},"value":"Complementary Product 1","style":1334104287060963,"overwrite-color":"auto","input":"inline"},"8":{"style":1334104287059641,"input":"inline"}},"18":{"5":{"style":1334170782081926},"2":{"style":1334184349727702},"10":{"style":1334170782081926},"9":{"style":1334170782081926},"6":{"style":1334170782081926},"3":{"style":1334170782081926},"11":{"style":1334170782081926},"7":{"style":1334170782081926},"4":{"style":1334170782081926},"8":{"style":1334170782081926}},"33":{"5":{"formula":"","value":"","style":1334104287060963,"overwrite-color":"auto","input":"inline"},"2":{"formula":"","value":"","style":1334104382982318,"overwrite-color":"auto"},"10":{"input":"inline"},"9":{"input":"inline"},"6":{"formula":"","value":"","style":1334104287060963,"overwrite-color":"auto","input":"inline"},"3":{"formula":"","value":"","style":1334104287060963,"overwrite-color":"auto"},"11":{"input":"inline"},"7":{"style":1334104287059641,"input":"inline"},"4":{"formula":"","value":"","style":1334104287060963,"overwrite-color":"auto","input":"inline"},"8":{"style":1334104287059641,"input":"inline"}},"15":{"5":{"style":1334170782081926},"2":{"formula":"Problem Hypothesis","merge":{"right":1,"down":0},"value":"Problem Hypothesis","style":1334182858130870,"overwrite-color":"auto"},"9":{"style":1334170782081926},"6":{"style":1334170782081926},"3":{"style":1334170782081926},"7":{"style":1334170782081926},"4":{"formula":"=T(../prob_work/D25)","merge":{"right":7,"down":0},"value":"This is another problem statement","style":1334170782082689,"overwrite-color":"auto"},"8":{"style":1334170782081926}},"29":{"5":{"formula":"","value":"","style":1334104287060963,"overwrite-color":"auto"},"2":{"formula":"","value":"","style":1334104382982318,"overwrite-color":"auto"},"6":{"formula":"","value":"","style":1334104287060963,"overwrite-color":"auto"},"3":{"formula":"","value":"","style":1334104287060963,"overwrite-color":"auto"},"7":{"style":1334104287059641},"4":{"formula":"Competitive Service 1","merge":{"right":7,"down":0},"value":"Competitive Service 1","style":1334104287060963,"overwrite-color":"auto","input":"inline"},"8":{"style":1334104287059641}},"47":{"5":{"formula":"","value":"","style":1332328896967086,"overwrite-color":"auto"},"2":{"formula":"","value":"","style":1332328896967086,"overwrite-color":"auto"},"6":{"formula":"","value":"","style":1332328896967086,"overwrite-color":"auto"},"3":{"formula":"","value":"","style":1332328896967086,"overwrite-color":"auto"},"4":{"formula":"","value":"","style":1332328896967086,"overwrite-color":"auto"}},"12":{"2":{"formula":"","value":"","style":1332328896967086,"overwrite-color":"auto"}},"30":{"5":{"formula":"","value":"","style":1334104287060963,"overwrite-color":"auto","input":"inline"},"2":{"formula":"Observations","merge":{"right":1,"down":0},"value":"Observations","style":1334104287067931,"overwrite-color":"auto"},"9":{"input":"inline"},"10":{"input":"inline"},"6":{"formula":"","value":"","style":1334104287060963,"overwrite-color":"auto","input":"inline"},"3":{"formula":"","value":"","style":1334104287060963,"overwrite-color":"auto"},"11":{"input":"inline"},"7":{"style":1334104287059641,"input":"inline"},"4":{"formula":"Competitive Observations","merge":{"right":7,"down":4},"value":"Competitive Observations","style":1334104287060963,"overwrite-color":"auto","input":"inline"},"8":{"style":1334104287059641,"input":"inline"}},"44":{"5":{"formula":"","value":"","style":1332328896967086,"overwrite-color":"auto"},"2":{"formula":"","value":"","style":1332328896967086,"overwrite-color":"auto"},"6":{"formula":"","value":"","style":1332328896967086,"overwrite-color":"auto"},"3":{"formula":"","value":"","style":1332328896967086,"overwrite-color":"auto"},"4":{"formula":"","value":"","style":1332328896967086,"overwrite-color":"auto"}},"8":{"5":{"style":1334170782081926},"2":{"formula":"Last Edited","merge":{"right":1,"down":0},"value":"Last Edited","style":1332329045542997,"overwrite-color":"auto"},"4":{"formula":"=../C9","merge":{"right":1,"down":0},"value":"04-Nov-2012","style":1334170782082689,"overwrite-color":"auto"}},"26":{"5":{"style":1334170782081926},"2":{"style":1334170782081926},"9":{"style":1334170782081926},"10":{"style":1334170782081926},"6":{"style":1334170782081926},"3":{"style":1334170782081926},"11":{"style":1334170782081926},"7":{"style":1334170782081926},"4":{"style":1334170782081926},"8":{"style":1334170782081926}}}}