{"time":1268318713827244,"user":"anonymous","host":"http://s.localhost:9002","lang":"en_gb","groups":[],"views":["_g/admin/acquisition_figures","_g/admin/acquisition_view","_g/core/spreadsheet"],"page":{},"styles":{"5":"color:#669900;background-color:#CCCCCC;font-weight:bold;text-align:left;","2":"color:#DDBEC3;font-weight:bold;font-size:20px;text-align:left;white-space:normal;","19":"color:#DDBEC3;font-weight:bold;white-space:normal;","20":"font-weight:bold;font-size:16px;text-align:left;","16":"background-color:#FFFDD0;text-align:left;","13":"font-weight:bold;font-size:16px;text-align:left;white-space:normal;","9":"text-align:left;white-space:normal;","10":"background-color:#DDBEC3;font-weight:bold;text-align:left;","6":"color:#669900;background-color:#CCCCCC;text-align:left;","3":"text-align:right;","21":"color:#FF7E00;background-color:#FFFDD0;font-weight:bold;font-size:16px;","17":"color:#DDBEC3;font-weight:bold;font-size:16px;text-align:left;","14":"color:#669900;background-color:#CCCCCC;font-weight:bold;text-align:center;","11":"color:#000000;background-color:#DDBEC3;font-weight:bold;text-align:center;","7":"color:#669900;background-color:#CCCCCC;text-align:left;white-space:normal;","4":"background-color:#FFFDD0;text-align:right;","1":"text-align:left;","18":"background-color:#FFFDD0;font-weight:bold;font-size:16px;","15":"color:#DDBEC3;font-weight:bold;font-size:16px;text-align:left;white-space:normal;","12":"background-color:#DDBEC3;font-weight:bold;text-align:center;","8":"text-align:center;"},"row":{"13":{"13":{"height":152}},"31":{"31":{"height":136}},"22":{"22":{"height":169}},"40":{"40":{"height":161}},"15":{"15":{"height":24}}},"column":{"2":{"2":{"width":218}},"3":{"3":{"width":240}}},"cell":{"23":{"2":{"style":1}},"2":{"2":{"rawvalue":"Acquisition Statistics","formula":"Acquisition Statistics","parents":"bleh","value":"<p>Acquisition Statistics</p>","style":2,"overwrite-color":"auto"}},"19":{"5":{"rawvalue":0,"formula":"0","value":"0.00","parents":"bleh","style":4,"format":"0.00","overwrite-color":"auto"},"2":{"rawvalue":"orange","formula":"=B10","parents":"bleh","value":"<p>orange</p>","style":5,"overwrite-color":"auto"},"9":{"rawvalue":0,"formula":"0","value":"0.00","parents":"bleh","style":4,"format":"0.00","overwrite-color":"auto"},"6":{"rawvalue":0,"formula":"0","value":"0.00","parents":"bleh","style":4,"format":"0.00","overwrite-color":"auto"},"3":{"rawvalue":"Facebook App","formula":"=C10","parents":"bleh","value":"<p>Facebook App</p>","style":6,"overwrite-color":"auto"},"7":{"rawvalue":0,"formula":"0","value":"0.00","parents":"bleh","style":4,"format":"0.00","overwrite-color":"auto"},"4":{"rawvalue":0,"formula":"0","value":"0.00","parents":"bleh","style":4,"format":"0.00","overwrite-color":"auto"},"8":{"rawvalue":0,"formula":"0","value":"0.00","parents":"bleh","style":4,"format":"0.00","overwrite-color":"auto"}},"20":{"5":{"rawvalue":11,"formula":"11","value":"11.00","parents":"bleh","style":4,"format":"0.00","overwrite-color":"auto"},"2":{"rawvalue":"black","formula":"=B11","parents":"bleh","value":"<p>black</p>","style":5,"overwrite-color":"auto"},"9":{"rawvalue":15,"formula":"15","value":"15.00","parents":"bleh","style":4,"format":"0.00","overwrite-color":"auto"},"6":{"rawvalue":12,"formula":"12","value":"12.00","parents":"bleh","style":4,"format":"0.00","overwrite-color":"auto"},"3":{"rawvalue":"Affiliates","formula":"=C11","parents":"bleh","value":"<p>Affiliates</p>","style":6,"overwrite-color":"auto"},"7":{"rawvalue":13,"formula":"13","value":"13.00","parents":"bleh","style":4,"format":"0.00","overwrite-color":"auto"},"4":{"rawvalue":10,"formula":"10","value":"10.00","parents":"bleh","style":4,"format":"0.00","overwrite-color":"auto"},"8":{"rawvalue":14,"formula":"14","value":"14.00","parents":"bleh","style":4,"format":"0.00","overwrite-color":"auto"}},"37":{"5":{"rawvalue":0,"formula":"=E19*../activation/D47","parents":"bleh","value":"0.00","style":3,"format":"0.00","overwrite-color":"auto"},"2":{"rawvalue":"orange","formula":"=B10","parents":"bleh","value":"<p>orange</p>","style":5,"overwrite-color":"auto"},"9":{"rawvalue":0.0,"formula":"=I19*../activation/D51","parents":"bleh","value":"0.00","style":3,"format":"0.00","overwrite-color":"auto"},"6":{"rawvalue":0,"formula":"=F19*../activation/D38","parents":"bleh","value":"0.00","style":3,"format":"0.00","overwrite-color":"auto"},"3":{"rawvalue":"Facebook App","formula":"=C10","parents":"bleh","value":"<p>Facebook App</p>","style":5,"overwrite-color":"auto"},"7":{"rawvalue":0.0,"formula":"=G19*../activation/D49","parents":"bleh","value":"0.00","style":3,"format":"0.00","overwrite-color":"auto"},"4":{"rawvalue":0,"formula":"=D19*../activation/D46","parents":"bleh","value":"0.00","style":3,"format":"0.00","overwrite-color":"auto"},"8":{"rawvalue":0.0,"formula":"=H19*../activation/D50","parents":"bleh","value":"0.00","style":3,"format":"0.00","overwrite-color":"auto"}},"16":{"5":{"rawvalue":0,"formula":"0","value":"0.00","parents":"bleh","style":4,"format":"0.00","overwrite-color":"auto"},"2":{"rawvalue":"red","formula":"=B7","parents":"bleh","value":"<p>red</p>","style":5,"overwrite-color":"auto"},"9":{"rawvalue":0,"formula":"0","value":"0.00","parents":"bleh","style":4,"format":"0.00","overwrite-color":"auto"},"6":{"rawvalue":0,"formula":"0","value":"0.00","parents":"bleh","style":4,"format":"0.00","overwrite-color":"auto"},"3":{"rawvalue":"SEO","formula":"=C7","parents":"bleh","value":"<p>SEO</p>","style":7,"overwrite-color":"auto"},"7":{"rawvalue":0,"formula":"0","value":"0.00","parents":"bleh","style":4,"format":"0.00","overwrite-color":"auto"},"4":{"rawvalue":0,"formula":"0","value":"0.00","parents":"bleh","style":4,"format":"0.00","overwrite-color":"auto"},"8":{"rawvalue":0,"formula":"0","value":"0.00","parents":"bleh","style":4,"format":"0.00","overwrite-color":"auto"}},"34":{"5":{"rawvalue":0.0,"formula":"=E16*../activation/d17","parents":"bleh","value":"0.00","style":3,"format":"0.00","overwrite-color":"auto"},"2":{"rawvalue":"red","formula":"=B7","parents":"bleh","value":"<p>red</p>","style":5,"overwrite-color":"auto"},"9":{"rawvalue":0.0,"formula":"=I16*../activation/d21","parents":"bleh","value":"0.00","style":3,"format":"0.00","overwrite-color":"auto"},"6":{"rawvalue":0.0,"formula":"=F16*../activation/d18","parents":"bleh","value":"0.00","style":3,"format":"0.00","overwrite-color":"auto"},"3":{"rawvalue":"SEO","formula":"=C7","parents":"bleh","value":"<p>SEO</p>","style":5,"overwrite-color":"auto"},"7":{"rawvalue":0.0,"formula":"=G16*../activation/d19","parents":"bleh","value":"0.00","style":3,"format":"0.00","overwrite-color":"auto"},"4":{"rawvalue":0.0,"formula":"=D16*../activation/d16","parents":"bleh","value":"0.00","style":3,"format":"0.00","overwrite-color":"auto"},"8":{"rawvalue":0.0,"formula":"=H16*../activation/d20","parents":"bleh","value":"0.00","style":3,"format":"0.00","overwrite-color":"auto"}},"13":{"3":{"rawvalue":"![graph](http://chart.apis.google.com/chart?chs=350x150&amp;chd=t:1,2,3,4,5,6|5,10,15,20,20,25|9,14,19,24,29,34|13,18,23,28,33,38|17,22,27,32,37,42&amp;cht=lc&amp;chds=0,50&amp;chxt=x,y&amp;chxl=0:|Jan|Fed|Mar|April|May|June|1:|0|50&amp;chco=FF0000,0000FF,008000,FFA500,000000)","formula":"=linegraph(D7:I11,1, 0, 50,d6:i6,B7:B11)","parents":"bleh","value":"<p><img src=\"http://chart.apis.google.com/chart?chs=350x150&amp;chd=t:1,2,3,4,5,6|5,10,15,20,20,25|9,14,19,24,29,34|13,18,23,28,33,38|17,22,27,32,37,42&amp;cht=lc&amp;chds=0,50&amp;chxt=x,y&amp;chxl=0:|Jan|Fed|Mar|April|May|June|1:|0|50&amp;chco=FF0000,0000FF,008000,FFA500,000000\" alt=\"graph\" title=\"\" /></p>","style":1,"format":"Markdown","overwrite-color":"auto"}},"31":{"5":{"style":3},"6":{"style":3},"3":{"rawvalue":"![graph](http://chart.apis.google.com/chart?chs=350x150&amp;chd=t:0,0,0,0,0,0|5000,10000,30000,60000,100000,30000|0,0,0,0,0,0|0,0,0,0,0,0|170000,242000,324000,416000,518000,630000&amp;cht=lc&amp;chds=0,750000&amp;chxt=x,y&amp;chxl=0:|Jan|Fed|Mar|April|May|June|1:|0|750000&amp;chco=FF0000,0000FF,008000,FFA500,000000)","formula":"=LINEGRAPH(D25:I29,1,0,750000,D24:I24,B25:B29)","parents":"bleh","value":"<p><img src=\"http://chart.apis.google.com/chart?chs=350x150&amp;chd=t:0,0,0,0,0,0|5000,10000,30000,60000,100000,30000|0,0,0,0,0,0|0,0,0,0,0,0|170000,242000,324000,416000,518000,630000&amp;cht=lc&amp;chds=0,750000&amp;chxt=x,y&amp;chxl=0:|Jan|Fed|Mar|April|May|June|1:|0|750000&amp;chco=FF0000,0000FF,008000,FFA500,000000\" alt=\"graph\" title=\"\" /></p>","style":9,"format":"Markdown","overwrite-color":"auto"}},"10":{"5":{"rawvalue":18,"formula":"=D10+5","parents":"bleh","value":"18","style":4,"overwrite-color":"auto"},"2":{"rawvalue":"orange","formula":"orange","parents":"bleh","value":"<p>orange</p>","style":10,"overwrite-color":"auto"},"9":{"rawvalue":38,"formula":"=H10+5","parents":"bleh","value":"38","style":4,"overwrite-color":"auto"},"6":{"rawvalue":23,"formula":"=E10+5","parents":"bleh","value":"23","style":4,"overwrite-color":"auto"},"3":{"rawvalue":"Facebook App","formula":"Facebook App","parents":"bleh","value":"<p>Facebook App</p>","style":10,"overwrite-color":"auto"},"7":{"rawvalue":28,"formula":"=F10+5","parents":"bleh","value":"28","style":4,"overwrite-color":"auto"},"4":{"rawvalue":13,"formula":"=D9+4","parents":"bleh","value":"13","style":4,"overwrite-color":"auto"},"8":{"rawvalue":33,"formula":"=G10+5","parents":"bleh","value":"33","style":4,"overwrite-color":"auto"}},"9":{"5":{"rawvalue":14,"formula":"=D9+5","parents":"bleh","value":"14","style":4,"overwrite-color":"auto"},"2":{"rawvalue":"green","formula":"green","parents":"bleh","value":"<p>green</p>","style":10,"overwrite-color":"auto"},"9":{"rawvalue":34,"formula":"=H9+5","parents":"bleh","value":"34","style":4,"overwrite-color":"auto"},"6":{"rawvalue":19,"formula":"=E9+5","parents":"bleh","value":"19","style":4,"overwrite-color":"auto"},"3":{"rawvalue":"iPhone App","formula":"iPhone App","parents":"bleh","value":"<p>iPhone App</p>","style":10,"overwrite-color":"auto"},"7":{"rawvalue":24,"formula":"=F9+5","parents":"bleh","value":"24","style":4,"overwrite-color":"auto"},"4":{"rawvalue":9,"formula":"=D8+4","parents":"bleh","value":"9","style":4,"overwrite-color":"auto"},"8":{"rawvalue":29,"formula":"=G9+5","parents":"bleh","value":"29","style":4,"overwrite-color":"auto"}},"27":{"5":{"rawvalue":0,"formula":"=E9*E18*1000","parents":"bleh","value":"0","style":4,"format":"0","overwrite-color":"auto"},"2":{"rawvalue":"green","formula":"=B9","parents":"bleh","value":"<p>green</p>","style":5,"overwrite-color":"auto"},"9":{"rawvalue":0,"formula":"=I9*I18*1000","parents":"bleh","value":"0","style":4,"format":"0","overwrite-color":"auto"},"6":{"rawvalue":0,"formula":"=F9*F18*1000","parents":"bleh","value":"0","style":4,"format":"0","overwrite-color":"auto"},"3":{"rawvalue":"iPhone App","formula":"=C9","parents":"bleh","value":"<p>iPhone App</p>","style":5,"overwrite-color":"auto"},"7":{"rawvalue":0,"formula":"=G9*G18*1000","parents":"bleh","value":"0","style":4,"format":"0","overwrite-color":"auto"},"4":{"rawvalue":0,"formula":"=D9*D18*1000","parents":"bleh","value":"0","style":4,"format":"0","overwrite-color":"auto"},"8":{"rawvalue":0,"formula":"=H9*H18*1000","parents":"bleh","value":"0","style":4,"format":"0","overwrite-color":"auto"}},"6":{"5":{"rawvalue":"Fed","formula":"Fed","parents":"bleh","value":"<p>Fed</p>","style":11,"overwrite-color":"auto"},"9":{"rawvalue":"June","formula":"June","parents":"bleh","value":"<p>June</p>","style":12,"overwrite-color":"auto"},"6":{"rawvalue":"Mar","formula":"Mar","parents":"bleh","value":"<p>Mar</p>","style":12,"overwrite-color":"auto"},"3":{"rawvalue":"## Channels By Volume (K's)","formula":"## Channels By Volume (K's)","value":"<h2>Channels By Volume (K's)</h2>","parents":"bleh","style":13,"format":"Markdown","overwrite-color":"auto"},"7":{"rawvalue":"April","formula":"April","parents":"bleh","value":"<p>April</p>","style":12,"overwrite-color":"auto"},"4":{"rawvalue":"Jan","formula":"Jan","parents":"bleh","value":"<p>Jan</p>","style":11,"overwrite-color":"auto"},"8":{"rawvalue":"May","formula":"May","parents":"bleh","value":"<p>May</p>","style":12,"overwrite-color":"auto"}},"24":{"5":{"rawvalue":"Fed","formula":"=E6","parents":"bleh","value":"<p>Fed</p>","style":14,"overwrite-color":"auto"},"9":{"rawvalue":"June","formula":"=I6","parents":"bleh","value":"<p>June</p>","style":14,"overwrite-color":"auto"},"6":{"rawvalue":"Mar","formula":"=F6","parents":"bleh","value":"<p>Mar</p>","style":14,"overwrite-color":"auto"},"3":{"rawvalue":"## Cost Per Channel ($)","formula":"## Cost Per Channel ($)","value":"<h2>Cost Per Channel ($)</h2>","parents":"bleh","style":13,"format":"Markdown","overwrite-color":"auto"},"7":{"rawvalue":"April","formula":"=G6","parents":"bleh","value":"<p>April</p>","style":14,"overwrite-color":"auto"},"4":{"rawvalue":"Jan","formula":"=D6","parents":"bleh","value":"<p>Jan</p>","style":14,"overwrite-color":"auto"},"8":{"rawvalue":"May","formula":"=H6","parents":"bleh","value":"<p>May</p>","style":14,"overwrite-color":"auto"}},"42":{"2":{"rawvalue":"Footer","formula":"Footer","parents":"bleh","value":"<p>Footer</p>","style":15,"overwrite-color":"auto"},"3":{"rawvalue":"[home][1] | [view graphs][2] | [view figures][3] | [view as spreadsheet][4]\n\n\n  [1]: /\n  [2]: ./?view=_g/admin/acquisition_view\n  [3]: ./?view=_g/admin/acquisition_figures\n  [4]: ./?view=_g/core/spreadsheet","formula":"[home][1] | [view graphs][2] | [view figures][3] | [view as spreadsheet][4]\n\n\n  [1]: /\n  [2]: ./?view=_g/admin/acquisition_view\n  [3]: ./?view=_g/admin/acquisition_figures\n  [4]: ./?view=_g/core/spreadsheet","value":"<p><a href=\"/\">home</a> | <a href=\"./?view=_g/admin/acquisition_view\">view graphs</a> | <a href=\"./?view=_g/admin/acquisition_figures\">view figures</a> | <a href=\"./?view=_g/core/spreadsheet\">view as spreadsheet</a></p>","parents":"bleh","style":1,"format":"Markdown","overwrite-color":"auto"}},"38":{"5":{"rawvalue":3.9600000000000004,"formula":"=E20*../activation/D57","parents":"bleh","value":"3.96","style":3,"format":"0.00","overwrite-color":"auto"},"2":{"rawvalue":"black","formula":"=B11","parents":"bleh","value":"<p>black</p>","style":5,"overwrite-color":"auto"},"9":{"rawvalue":0,"formula":"=I20*../activation/D61","parents":"bleh","value":"0.00","style":3,"format":"0.00","overwrite-color":"auto"},"6":{"rawvalue":4.800000000000001,"formula":"=F20*../activation/D58","parents":"bleh","value":"4.80","style":3,"format":"0.00","overwrite-color":"auto"},"3":{"rawvalue":"Affiliates","formula":"=C11","parents":"bleh","value":"<p>Affiliates</p>","style":5,"overwrite-color":"auto"},"7":{"rawvalue":0,"formula":"=G20*../activation/D59","parents":"bleh","value":"0.00","style":3,"format":"0.00","overwrite-color":"auto"},"4":{"rawvalue":3.2400000000000007,"formula":"=D20*../activation/D56","parents":"bleh","value":"3.24","style":3,"format":"0.00","overwrite-color":"auto"},"8":{"rawvalue":0,"formula":"=H20*../activation/D60","parents":"bleh","value":"0.00","style":3,"format":"0.00","overwrite-color":"auto"}},"17":{"5":{"rawvalue":2,"formula":"2","value":"2.00","parents":"bleh","style":4,"format":"0.00","overwrite-color":"auto"},"2":{"rawvalue":"blue","formula":"=B8","parents":"bleh","value":"<p>blue</p>","style":5,"overwrite-color":"auto"},"9":{"rawvalue":6,"formula":"6","value":"6.00","parents":"bleh","style":4,"format":"0.00","overwrite-color":"auto"},"6":{"rawvalue":3,"formula":"3","value":"3.00","parents":"bleh","style":4,"format":"0.00","overwrite-color":"auto"},"3":{"rawvalue":"Ad-Sense","formula":"=C8","parents":"bleh","value":"<p>Ad-Sense</p>","style":6,"overwrite-color":"auto"},"7":{"rawvalue":4,"formula":"4","value":"4.00","parents":"bleh","style":4,"format":"0.00","overwrite-color":"auto"},"4":{"rawvalue":1,"formula":"1","value":"1.00","parents":"bleh","style":4,"format":"0.00","overwrite-color":"auto"},"8":{"rawvalue":5,"formula":"5","value":"5.00","parents":"bleh","style":4,"format":"0.00","overwrite-color":"auto"}},"35":{"5":{"rawvalue":0.7200000000000001,"formula":"=E17*../activation/d27","parents":"bleh","value":"0.72","style":3,"format":"0.00","overwrite-color":"auto"},"2":{"rawvalue":"blue","formula":"=B8","parents":"bleh","value":"<p>blue</p>","style":5,"overwrite-color":"auto"},"9":{"rawvalue":0,"formula":"=I17*../activation/d31","parents":"bleh","value":"0.00","style":3,"format":"0.00","overwrite-color":"auto"},"6":{"rawvalue":1.2000000000000002,"formula":"=F17*../activation/d28","parents":"bleh","value":"1.20","style":3,"format":"0.00","overwrite-color":"auto"},"3":{"rawvalue":"Ad-Sense","formula":"=C8","parents":"bleh","value":"<p>Ad-Sense</p>","style":5,"overwrite-color":"auto"},"7":{"rawvalue":0,"formula":"=G17*../activation/d29","parents":"bleh","value":"0.00","style":3,"format":"0.00","overwrite-color":"auto"},"4":{"rawvalue":0.32400000000000007,"formula":"=D17*../activation/D26","parents":"bleh","value":"0.32","style":3,"format":"0.00","overwrite-color":"auto"},"8":{"rawvalue":0,"formula":"=H17*../activation/d30","parents":"bleh","value":"0.00","style":3,"format":"0.00","overwrite-color":"auto"}},"11":{"5":{"rawvalue":22,"formula":"=D11+5","parents":"bleh","value":"22","style":4,"overwrite-color":"auto"},"2":{"rawvalue":"black","formula":"black","parents":"bleh","value":"<p>black</p>","style":10,"overwrite-color":"auto"},"9":{"rawvalue":42,"formula":"=H11+5","parents":"bleh","value":"42","style":4,"overwrite-color":"auto"},"6":{"rawvalue":27,"formula":"=E11+5","parents":"bleh","value":"27","style":4,"overwrite-color":"auto"},"3":{"rawvalue":"Affiliates","formula":"Affiliates","parents":"bleh","value":"<p>Affiliates</p>","style":10,"overwrite-color":"auto"},"7":{"rawvalue":32,"formula":"=F11+5","parents":"bleh","value":"32","style":4,"overwrite-color":"auto"},"4":{"rawvalue":17,"formula":"=D10+4","parents":"bleh","value":"17","style":4,"overwrite-color":"auto"},"8":{"rawvalue":37,"formula":"=G11+5","parents":"bleh","value":"37","style":4,"overwrite-color":"auto"}},"28":{"5":{"rawvalue":0,"formula":"=E10*E19*1000","parents":"bleh","value":"0","style":4,"format":"0","overwrite-color":"auto"},"2":{"rawvalue":"orange","formula":"=B10","parents":"bleh","value":"<p>orange</p>","style":5,"overwrite-color":"auto"},"9":{"rawvalue":0,"formula":"=I10*I19*1000","parents":"bleh","value":"0","style":4,"format":"0","overwrite-color":"auto"},"6":{"rawvalue":0,"formula":"=F10*F19*1000","parents":"bleh","value":"0","style":4,"format":"0","overwrite-color":"auto"},"3":{"rawvalue":"Facebook App","formula":"=C10","parents":"bleh","value":"<p>Facebook App</p>","style":5,"overwrite-color":"auto"},"7":{"rawvalue":0,"formula":"=G10*G19*1000","parents":"bleh","value":"0","style":4,"format":"0","overwrite-color":"auto"},"4":{"rawvalue":0,"formula":"=D10*D19*1000","parents":"bleh","value":"0","style":4,"format":"0","overwrite-color":"auto"},"8":{"rawvalue":0,"formula":"=H10*H19*1000","parents":"bleh","value":"0","style":4,"format":"0","overwrite-color":"auto"}},"25":{"5":{"rawvalue":0,"formula":"=E7*E16*1000","parents":"bleh","value":"0","style":4,"format":"0","overwrite-color":"auto"},"2":{"rawvalue":"red","formula":"=b7","parents":"bleh","value":"<p>red</p>","style":5,"overwrite-color":"auto"},"9":{"rawvalue":0,"formula":"=I7*I16*1000","parents":"bleh","value":"0","style":4,"format":"0","overwrite-color":"auto"},"6":{"rawvalue":0,"formula":"=F7*F16*1000","parents":"bleh","value":"0","style":4,"format":"0","overwrite-color":"auto"},"3":{"rawvalue":"SEO","formula":"=C7","parents":"bleh","value":"<p>SEO</p>","style":5,"overwrite-color":"auto"},"7":{"rawvalue":0,"formula":"=G7*G16*1000","value":"0","parents":"bleh","format":"0","style":4,"overwrite-color":"auto"},"4":{"rawvalue":0,"formula":"=D7*D16*1000","parents":"bleh","value":"0","style":4,"format":"0","overwrite-color":"auto"},"8":{"rawvalue":0,"formula":"=H7*H16*1000","parents":"bleh","value":"0","style":4,"format":"0","overwrite-color":"auto"}},"7":{"5":{"rawvalue":2,"formula":"2","parents":"bleh","value":"2","style":4,"overwrite-color":"auto"},"2":{"rawvalue":"red","formula":"red","parents":"bleh","value":"<p>red</p>","style":10,"overwrite-color":"auto"},"9":{"rawvalue":6,"formula":"6","parents":"bleh","value":"6","style":4,"overwrite-color":"auto"},"6":{"rawvalue":3,"formula":"3","parents":"bleh","value":"3","style":4,"overwrite-color":"auto"},"3":{"rawvalue":"SEO","formula":"SEO","parents":"bleh","value":"<p>SEO</p>","style":10,"overwrite-color":"auto"},"7":{"rawvalue":4,"formula":"4","parents":"bleh","value":"4","style":4,"overwrite-color":"auto"},"4":{"rawvalue":1,"formula":"1","parents":"bleh","value":"1","style":4,"overwrite-color":"auto"},"1":{"rawvalue":"### Key","formula":"### Key","value":"<h3>Key</h3>","parents":"bleh","style":16,"format":"Markdown","overwrite-color":"auto"},"8":{"rawvalue":5,"formula":"5","parents":"bleh","value":"5","style":4,"overwrite-color":"auto"}},"4":{"2":{"rawvalue":"Title","formula":"Title","parents":"bleh","value":"<p>Title</p>","style":17,"overwrite-color":"auto"},"3":{"rawvalue":"Acquisition Statistics","formula":"Acquisition Statistics","parents":"bleh","value":"<p>Acquisition Statistics</p>","style":21,"overwrite-color":"auto"}},"22":{"3":{"rawvalue":"![graph](http://chart.apis.google.com/chart?chs=350x150&amp;chd=t:0,0,0,0,0,0|1,2,3,4,5,6|0,0,0,0,0,0|0,0,0,0,0,0|10,11,12,13,14,15&amp;cht=lc&amp;chds=0,20&amp;chxt=x,y&amp;chxl=0:|Jan|Fed|Mar|April|May|June|1:|0|20&amp;chco=FF0000,0000FF,008000,FFA500,000000)","formula":"=LINEGRAPH(D16:I20,1,0,20,D15:I15,B16:B20)","parents":"bleh","value":"<p><img src=\"http://chart.apis.google.com/chart?chs=350x150&amp;chd=t:0,0,0,0,0,0|1,2,3,4,5,6|0,0,0,0,0,0|0,0,0,0,0,0|10,11,12,13,14,15&amp;cht=lc&amp;chds=0,20&amp;chxt=x,y&amp;chxl=0:|Jan|Fed|Mar|April|May|June|1:|0|20&amp;chco=FF0000,0000FF,008000,FFA500,000000\" alt=\"graph\" title=\"\" /></p>","style":1,"format":"Markdown","overwrite-color":"auto"}},"40":{"3":{"rawvalue":"![graph](http://chart.apis.google.com/chart?chs=350x150&amp;chd=t:0,0,0,0,0,0|0.32400000000000007,0.7200000000000001,1.2000000000000002,0,0,0|0,0,0,0,0,0|0,0,0,0,0,0|3.2400000000000007,3.9600000000000004,4.800000000000001,0,0,0&amp;cht=lc&amp;chds=0,5&amp;chxt=x,y&amp;chxl=0:|Jan|Fed|Mar|April|May|June|1:|0|5&amp;chco=FF0000,0000FF,008000,FFA500,000000)","formula":"=LINEGRAPH(D34:I38,1,0,5,D33:I33,B34:B38)","parents":"bleh","value":"<p><img src=\"http://chart.apis.google.com/chart?chs=350x150&amp;chd=t:0,0,0,0,0,0|0.32400000000000007,0.7200000000000001,1.2000000000000002,0,0,0|0,0,0,0,0,0|0,0,0,0,0,0|3.2400000000000007,3.9600000000000004,4.800000000000001,0,0,0&amp;cht=lc&amp;chds=0,5&amp;chxt=x,y&amp;chxl=0:|Jan|Fed|Mar|April|May|June|1:|0|5&amp;chco=FF0000,0000FF,008000,FFA500,000000\" alt=\"graph\" title=\"\" /></p>","style":9,"format":"Markdown","overwrite-color":"auto"}},"39":{"4":{"style":3}},"1":{"5":{"style":19}},"18":{"5":{"rawvalue":0,"formula":"0","value":"0.00","parents":"bleh","style":4,"format":"0.00","overwrite-color":"auto"},"2":{"rawvalue":"green","formula":"=B9","parents":"bleh","value":"<p>green</p>","style":5,"overwrite-color":"auto"},"9":{"rawvalue":0,"formula":"0","value":"0.00","parents":"bleh","style":4,"format":"0.00","overwrite-color":"auto"},"10":{"style":3},"6":{"rawvalue":0,"formula":"0","value":"0.00","parents":"bleh","style":4,"format":"0.00","overwrite-color":"auto"},"3":{"rawvalue":"iPhone App","formula":"=C9","parents":"bleh","value":"<p>iPhone App</p>","style":6,"overwrite-color":"auto"},"11":{"style":3},"7":{"rawvalue":0,"formula":"0","value":"0.00","parents":"bleh","style":4,"format":"0.00","overwrite-color":"auto"},"4":{"rawvalue":0,"formula":"0","value":"0.00","parents":"bleh","style":4,"format":"0.00","overwrite-color":"auto"},"8":{"rawvalue":0,"formula":"0","value":"0.00","parents":"bleh","style":4,"format":"0.00","overwrite-color":"auto"}},"36":{"5":{"rawvalue":0,"formula":"=E18*../activation/D37","parents":"bleh","value":"0.00","style":3,"format":"0.00","overwrite-color":"auto"},"2":{"rawvalue":"green","formula":"=B9","parents":"bleh","value":"<p>green</p>","style":5,"overwrite-color":"auto"},"9":{"rawvalue":0.0,"formula":"=I18*../activation/D41","parents":"bleh","value":"0.00","style":3,"format":"0.00","overwrite-color":"auto"},"6":{"rawvalue":0,"formula":"=F18*../activation/D38","parents":"bleh","value":"0.00","style":3,"format":"0.00","overwrite-color":"auto"},"3":{"rawvalue":"iPhone App","formula":"=C9","parents":"bleh","value":"<p>iPhone App</p>","style":5,"overwrite-color":"auto"},"7":{"rawvalue":0.0,"formula":"=G18*../activation/D39","parents":"bleh","value":"0.00","style":3,"format":"0.00","overwrite-color":"auto"},"4":{"rawvalue":0,"formula":"=D18*../activation/D36","parents":"bleh","value":"0.00","style":3,"format":"0.00","overwrite-color":"auto"},"8":{"rawvalue":0.0,"formula":"=H18*../activation/D40","parents":"bleh","value":"0.00","style":3,"format":"0.00","overwrite-color":"auto"}},"15":{"5":{"rawvalue":"Fed","formula":"=E6","parents":"bleh","value":"<p>Fed</p>","style":14,"overwrite-color":"auto"},"9":{"rawvalue":"June","formula":"=I6","parents":"bleh","value":"<p>June</p>","style":14,"overwrite-color":"auto"},"6":{"rawvalue":"Mar","formula":"=F6","parents":"bleh","value":"<p>Mar</p>","style":14,"overwrite-color":"auto"},"3":{"rawvalue":"## Cost Per User ($)","formula":"## Cost Per User ($)","value":"<h2>Cost Per User ($)</h2>","parents":"bleh","style":20,"format":"Markdown","overwrite-color":"auto"},"7":{"rawvalue":"April","formula":"=G6","parents":"bleh","value":"<p>April</p>","style":14,"overwrite-color":"auto"},"4":{"rawvalue":"Jan","formula":"=D6","parents":"bleh","value":"<p>Jan</p>","style":14,"overwrite-color":"auto"},"8":{"rawvalue":"May","formula":"=H6","parents":"bleh","value":"<p>May</p>","style":14,"overwrite-color":"auto"}},"33":{"5":{"rawvalue":"Fed","formula":"=E6","parents":"bleh","value":"<p>Fed</p>","style":14,"overwrite-color":"auto"},"9":{"rawvalue":"June","formula":"=I6","parents":"bleh","value":"<p>June</p>","style":14,"overwrite-color":"auto"},"6":{"rawvalue":"Mar","formula":"=F6","parents":"bleh","value":"<p>Mar</p>","style":14,"overwrite-color":"auto"},"3":{"rawvalue":"## Cost Per Activation ($)","formula":"## Cost Per Activation ($)","value":"<h2>Cost Per Activation ($)</h2>","parents":"bleh","style":13,"format":"Markdown","overwrite-color":"auto"},"7":{"rawvalue":"April","formula":"=G6","parents":"bleh","value":"<p>April</p>","style":14,"overwrite-color":"auto"},"4":{"rawvalue":"Jan","formula":"=D6","parents":"bleh","value":"<p>Jan</p>","style":14,"overwrite-color":"auto"},"8":{"rawvalue":"May","formula":"=H6","parents":"bleh","value":"<p>May</p>","style":14,"overwrite-color":"auto"}},"29":{"5":{"rawvalue":242000,"formula":"=E11*E20*1000","parents":"bleh","value":"242000","style":4,"format":"0","overwrite-color":"auto"},"2":{"rawvalue":"black","formula":"=B11","parents":"bleh","value":"<p>black</p>","style":5,"overwrite-color":"auto"},"9":{"rawvalue":630000,"formula":"=I11*I20*1000","parents":"bleh","value":"630000","style":4,"format":"0","overwrite-color":"auto"},"6":{"rawvalue":324000,"formula":"=F11*F20*1000","parents":"bleh","value":"324000","style":4,"format":"0","overwrite-color":"auto"},"3":{"rawvalue":"Affiliates","formula":"=C11","parents":"bleh","value":"<p>Affiliates</p>","style":5,"overwrite-color":"auto"},"7":{"rawvalue":416000,"formula":"=G11*G20*1000","parents":"bleh","value":"416000","style":4,"format":"0","overwrite-color":"auto"},"4":{"rawvalue":170000,"formula":"=D11*D20*1000","parents":"bleh","value":"170000","style":4,"format":"0","overwrite-color":"auto"},"8":{"rawvalue":518000,"formula":"=H11*H20*1000","parents":"bleh","value":"518000","style":4,"format":"0","overwrite-color":"auto"}},"8":{"5":{"rawvalue":10,"formula":"=D8+5","parents":"bleh","value":"10","style":4,"overwrite-color":"auto"},"2":{"rawvalue":"blue","formula":"blue","parents":"bleh","value":"<p>blue</p>","style":10,"overwrite-color":"auto"},"9":{"rawvalue":25,"formula":"=H8+5","parents":"bleh","value":"25","style":4,"overwrite-color":"auto"},"6":{"rawvalue":15,"formula":"=E8+5","parents":"bleh","value":"15","style":4,"overwrite-color":"auto"},"3":{"rawvalue":"Ad-Sense","formula":"Ad-Sense","parents":"bleh","value":"<p>Ad-Sense</p>","style":10,"overwrite-color":"auto"},"7":{"rawvalue":20,"formula":"=F8+5","parents":"bleh","value":"20","style":4,"overwrite-color":"auto"},"4":{"rawvalue":5,"formula":"=D7+4","parents":"bleh","value":"5","style":4,"overwrite-color":"auto"},"8":{"rawvalue":20,"formula":"=G8+5","parents":"bleh","value":"20","style":4,"overwrite-color":"auto"}},"26":{"5":{"rawvalue":10000,"formula":"=E8*E17*1000","value":"10000","parents":"bleh","style":4,"format":"0","overwrite-color":"auto"},"2":{"rawvalue":"blue","formula":"=B8","parents":"bleh","value":"<p>blue</p>","style":5,"overwrite-color":"auto"},"9":{"rawvalue":30000,"formula":"=I8*I17*1000","value":"30000","parents":"bleh","style":4,"format":"0","overwrite-color":"auto"},"6":{"rawvalue":30000,"formula":"=F8*F17*1000","value":"30000","parents":"bleh","style":4,"format":"0","overwrite-color":"auto"},"3":{"rawvalue":"Ad-Sense","formula":"=C8","parents":"bleh","value":"<p>Ad-Sense</p>","style":5,"overwrite-color":"auto"},"7":{"rawvalue":60000,"formula":"=G8*G17*1000","value":"60000","parents":"bleh","style":4,"format":"0","overwrite-color":"auto"},"4":{"rawvalue":5000,"formula":"=D8*D17*1000","value":"5000","parents":"bleh","style":4,"format":"0","overwrite-color":"auto"},"8":{"rawvalue":100000,"formula":"=H8*H17*1000","value":"100000","parents":"bleh","style":4,"format":"0","overwrite-color":"auto"}}}}
